pypsa_explorer/__init__.py
pypsa_explorer/app.py
pypsa_explorer/cli.py
pypsa_explorer/config.py
pypsa_explorer/py.typed
pypsa_explorer/callbacks/__init__.py
pypsa_explorer/callbacks/data_explorer.py
pypsa_explorer/callbacks/filters.py
pypsa_explorer/callbacks/navigation.py
pypsa_explorer/callbacks/network.py
pypsa_explorer/callbacks/theme.py
pypsa_explorer/callbacks/visualizations.py
pypsa_explorer/layouts/__init__.py
pypsa_explorer/layouts/components.py
pypsa_explorer/layouts/dashboard.py
pypsa_explorer/layouts/tabs.py
pypsa_explorer/layouts/welcome.py
pypsa_explorer/utils/__init__.py
pypsa_explorer/utils/data_table.py
pypsa_explorer/utils/helpers.py
pypsa_explorer/utils/network_loader.py
pypsa_explorer-0.1.0.dist-info/licenses/LICENSE
pypsa_explorer-0.1.0.dist-info/METADATA
pypsa_explorer-0.1.0.dist-info/WHEEL
pypsa_explorer-0.1.0.dist-info/entry_points.txt
pypsa_explorer-0.1.0.dist-info/top_level.txt
pypsa_explorer-0.1.0.dist-info/RECORD
