Metadata-Version: 2.4
Name: pypsa-explorer
Version: 0.1.0
Summary: Interactive dashboard for visualizing and analyzing PyPSA energy system networks
Author-email: Open Energy Transition <info@openenergytransition.org>
License-Expression: MIT
Project-URL: Homepage, https://github.com/openenergytransition/pypsa-explorer
Project-URL: Documentation, https://pypsa-explorer.readthedocs.io
Project-URL: Repository, https://github.com/openenergytransition/pypsa-explorer
Project-URL: Bug Tracker, https://github.com/openenergytransition/pypsa-explorer/issues
Keywords: pypsa,energy,visualization,dashboard,power-system
Classifier: Development Status :: 4 - Beta
Classifier: Intended Audience :: Science/Research
Classifier: Operating System :: OS Independent
Classifier: Programming Language :: Python :: 3
Classifier: Programming Language :: Python :: 3.12
Classifier: Programming Language :: Python :: 3.13
Classifier: Topic :: Scientific/Engineering
Classifier: Topic :: Scientific/Engineering :: Visualization
Requires-Python: >=3.12
License-File: LICENSE
Requires-Dist: plotly>=5.0
Requires-Dist: dash>=2.14
Requires-Dist: folium>=0.14
Requires-Dist: mapclassify>=2.5
Requires-Dist: dash-bootstrap-components>=1.5
Requires-Dist: pypsa>=1.0.3
Requires-Dist: pyyaml>=6.0
Requires-Dist: typer>=0.9
Requires-Dist: rich>=13.0
Provides-Extra: dev
Requires-Dist: pytest>=7.4; extra == "dev"
Requires-Dist: pytest-cov>=4.1; extra == "dev"
Requires-Dist: pytest-mock>=3.11; extra == "dev"
Requires-Dist: black>=23.0; extra == "dev"
Requires-Dist: ruff>=0.1; extra == "dev"
Requires-Dist: mypy>=1.5; extra == "dev"
Requires-Dist: pre-commit>=3.4; extra == "dev"
Requires-Dist: ipython>=8.0; extra == "dev"
Requires-Dist: jupyter>=1.0; extra == "dev"
Requires-Dist: nbconvert>=7.0; extra == "dev"
Provides-Extra: docs
Requires-Dist: sphinx>=7.0; extra == "docs"
Requires-Dist: sphinx-rtd-theme>=1.3; extra == "docs"
Requires-Dist: sphinx-autodoc-typehints>=1.24; extra == "docs"
Requires-Dist: myst-parser>=2.0; extra == "docs"
Provides-Extra: test
Requires-Dist: pytest>=7.4; extra == "test"
Requires-Dist: pytest-cov>=4.1; extra == "test"
Requires-Dist: pytest-mock>=3.11; extra == "test"
Dynamic: license-file
